import dis
b = 1
h = 1
def var2(g):
    return (b + h) & (432 / h) * ((6 + b) - g)
print(dis.dis(var2))

0 LOAD_GLOBAL 0 (b) - загрузка переменной в стек
2 LOAD_GLOBAL 1 (h) - загрузка переменной в стек
4 BINARY_ADD - сложение инструкций 0 и 2
6 LOAD_CONST 1 (432) - загрузка постоянной в стек
8 LOAD_GLOBAL 1 (h) - загрузка переменной в стек
10 BINARY_TRUE_DIVIDE - деление инструкции 6 на инструкцию 8
12 LOAD_CONST 2 (6) - загрузка постоянной в стек
14 LOAD_GLOBAL 0 (b) - загрузка переменной в стек
16 BINARY_ADD - сложение инструкций 12 и 14
18 LOAD_FAST 0 (g) - загрузка переменной в стек
20 BINARY_SUBTRACT - вычитание инструкции 18 из инструкции 16
22 BINARY_MULTIPLY - перемножение инструкции 20 с 10
24 BINARY_AND - побитовое "и"
26 RETURN_VALUE - возврат значения